{
  "macro": [
    {
      "title": "Inflation Fears",
      "impact": "MED",
      "confidence": 70,
      "body": "The recent surge in job openings and potential Iran war developments may lead to increased inflation. This could impact the portfolio's leveraged positions.",
      "bull": "A moderate inflation environment could boost the portfolio's growth-oriented holdings.",
      "bull_estimate": "+$20,000-$30,000 via FNGU/SPXL",
      "bull_probability": 40,
      "base": "A stable inflation environment would likely result in minimal net change for the portfolio.",
      "base_estimate": "±$5,000",
      "base_probability": 30,
      "bear": "High inflation could lead to decreased purchasing power and negatively impact the portfolio's value.",
      "bear_estimate": "-$30,000-$40,000",
      "bear_probability": 30
    },
    {
      "title": "Geopolitical Tensions",
      "impact": "HIGH",
      "confidence": 80,
      "body": "The ongoing US-Iran conflict and potential escalation could lead to market volatility. This may affect the portfolio's risk profile.",
      "bull": "A resolution to the conflict could lead to a relief rally, benefiting the portfolio's growth-oriented holdings.",
      "bull_estimate": "+$25,000-$35,000",
      "bull_probability": 35,
      "base": "A prolonged conflict could result in increased market volatility, potentially impacting the portfolio's value.",
      "base_estimate": "±$10,000",
      "base_probability": 40,
      "bear": "An escalation of the conflict could lead to a significant market downturn, negatively impacting the portfolio.",
      "bear_estimate": "-$40,000-$50,000",
      "bear_probability": 25
    },
    {
      "title": "AI-Driven Growth",
      "impact": "MED",
      "confidence": 60,
      "body": "The growing adoption of AI technology could lead to increased growth in the tech sector. This may benefit the portfolio's tech holdings.",
      "bull": "A continued AI-driven growth trend could lead to significant gains for the portfolio's tech holdings.",
      "bull_estimate": "+$30,000-$40,000",
      "bull_probability": 45,
      "base": "A stable AI growth environment would likely result in moderate gains for the portfolio's tech holdings.",
      "base_estimate": "+$10,000-$20,000",
      "base_probability": 35,
      "bear": "A slowdown in AI adoption could lead to decreased growth for the portfolio's tech holdings.",
      "bear_estimate": "-$15,000-$25,000",
      "bear_probability": 20
    }
  ],
  "risks": [
    {
      "title": "Leverage Risk",
      "level": "HIGH",
      "context": "49% of portfolio (~ $135K CAD) in leveraged ETFs",
      "body": "The portfolio's high leverage exposure amplifies both gains and losses, increasing risk."
    },
    {
      "title": "FX Risk",
      "level": "MED",
      "context": "68% USD exposure (~ $190K CAD) with FX book rate of 1.3925",
      "body": "The portfolio's significant USD exposure and FX book rate may result in currency-related losses."
    },
    {
      "title": "Concentration Risk",
      "level": "MED",
      "context": "Top 5 holdings account for ~60% of portfolio value",
      "body": "The portfolio's concentration in a few key holdings increases risk if any of these holdings experience significant declines."
    }
  ],
  "news": [
    {
      "headline": "NVIDIA AI PC Chip",
      "impact": "HIGH",
      "confidence": 85,
      "category": "Sector & Stock",
      "body": "NVIDIA's AI PC chip unveiling may lead to increased demand for NVDA and other AI-related stocks.",
      "exposure": "NVDA ~$43K CAD",
      "outcomes": [
        {
          "label": "Bull",
          "probability": 50,
          "scenario": "NVDA and other AI-related stocks experience significant gains.",
          "estimate": "+$10,000-$15,000"
        },
        {
          "label": "Base",
          "probability": 30,
          "scenario": "NVDA and other AI-related stocks experience moderate gains.",
          "estimate": "+$3,000-$6,000"
        },
        {
          "label": "Bear",
          "probability": 20,
          "scenario": "NVDA and other AI-related stocks experience declines.",
          "estimate": "-$5,000-$10,000"
        }
      ]
    },
    {
      "headline": "TSMC Price Hike",
      "impact": "MED",
      "confidence": 70,
      "category": "Sector & Stock",
      "body": "TSMC's price hike may negatively impact NVDA's margins and stock price.",
      "exposure": "NVDA ~$43K CAD, TSM ~$10K CAD",
      "outcomes": [
        {
          "label": "Bull",
          "probability": 30,
          "scenario": "NVDA and TSM experience minimal impact from the price hike.",
          "estimate": "±$1,000"
        },
        {
          "label": "Base",
          "probability": 40,
          "scenario": "NVDA and TSM experience moderate declines due to the price hike.",
          "estimate": "-$2,000-$4,000"
        },
        {
          "label": "Bear",
          "probability": 30,
          "scenario": "NVDA and TSM experience significant declines due to the price hike.",
          "estimate": "-$5,000-$10,000"
        }
      ]
    },
    {
      "headline": "HPE Guidance Hike",
      "impact": "MED",
      "confidence": 65,
      "category": "Sector & Stock",
      "body": "HPE's guidance hike may lead to increased demand for tech stocks, including AVGO and MSFT.",
      "exposure": "AVGO ~$12K CAD, MSFT ~$15K CAD",
      "outcomes": [
        {
          "label": "Bull",
          "probability": 40,
          "scenario": "AVGO and MSFT experience significant gains due to the guidance hike.",
          "estimate": "+$4,000-$8,000"
        },
        {
          "label": "Base",
          "probability": 35,
          "scenario": "AVGO and MSFT experience moderate gains due to the guidance hike.",
          "estimate": "+$1,500-$3,500"
        },
        {
          "label": "Bear",
          "probability": 25,
          "scenario": "AVGO and MSFT experience minimal impact from the guidance hike.",
          "estimate": "±$1,000"
        }
      ]
    }
  ],
  "picks": [
    {
      "ticker": "CRWD",
      "action": "ADD",
      "account": "RRSP",
      "thesis": "CrowdStrike's growth in the cybersecurity sector, driven by AI adoption, makes it an attractive addition to the portfolio.",
      "entry": "Entry price range: $150-$180"
    },
    {
      "ticker": "ZM",
      "action": "WATCH",
      "account": "Investment",
      "thesis": "Zoom's potential for growth in the video conferencing space, driven by remote work trends, makes it a stock to monitor for potential addition to the portfolio.",
      "entry": "Monitor for entry on a pullback to $200-$220"
    }
  ],
  "strengths": [
    {
      "ticker": null,
      "text": "Diversified portfolio with a mix of growth and income-generating holdings"
    },
    {
      "ticker": "NVDA",
      "text": "Strong growth potential in the AI and tech sectors"
    },
    {
      "ticker": "TSLA",
      "text": "Exposure to the growing electric vehicle market"
    },
    {
      "ticker": "MSFT",
      "text": "Stable cash flows and dividend payments"
    },
    {
      "ticker": "V",
      "text": "Growing payment processing industry and potential for expansion"
    }
  ],
  "concerns": [
    {
      "ticker": null,
      "text": "High leverage exposure increases risk"
    },
    {
      "ticker": "NVDA",
      "text": "Dependence on AI and tech sector growth"
    },
    {
      "ticker": "TSLA",
      "text": "Volatility in the electric vehicle market"
    },
    {
      "ticker": "SPXL",
      "text": "Concentration in a few key holdings increases risk"
    },
    {
      "ticker": "FNGU",
      "text": "Leveraged ETFs amplify both gains and losses"
    }
  ],
  "strategy_short": [
    {
      "num": "01",
      "text": "Monitor and adjust leverage exposure as needed to manage risk"
    },
    {
      "num": "02",
      "text": "Consider tax-loss harvesting to optimize portfolio performance"
    },
    {
      "num": "03",
      "text": "Maintain a cash allocation to take advantage of potential market opportunities"
    },
    {
      "num": "04",
      "text": "Review and adjust the portfolio's sector allocation to ensure diversification"
    }
  ],
  "strategy_mid": [
    {
      "num": "01",
      "text": "Continue to invest in growth-oriented holdings, such as tech and AI-related stocks"
    },
    {
      "num": "02",
      "text": "Diversify the portfolio by adding holdings from other sectors, such as healthcare or finance"
    },
    {
      "num": "03",
      "text": "Consider adding dividend-paying stocks to increase income generation"
    },
    {
      "num": "04",
      "text": "Review and adjust the portfolio's geographic allocation to ensure diversification"
    }
  ],
  "strategy_long": [
    {
      "num": "01",
      "text": "Maintain a long-term focus and avoid making emotional decisions based on short-term market fluctuations"
    },
    {
      "num": "02",
      "text": "Continue to invest in a tax-efficient manner, utilizing tax-advantaged accounts such as RRSPs and TFSAs"
    },
    {
      "num": "03",
      "text": "Review and adjust the portfolio's asset allocation to ensure it remains aligned with the investor's risk tolerance and goals"
    },
    {
      "num": "04",
      "text": "Consider adding alternative investments, such as real estate or private equity, to further diversify the portfolio"
    }
  ],
  "tax": {
    "tfsa": [
      {
        "icon": "✦",
        "text": "Utilize TFSA contributions to optimize tax-free growth"
      },
      {
        "icon": "✦",
        "text": "Consider transferring non-registered holdings to a TFSA to reduce tax liability"
      }
    ],
    "fhsa": [
      {
        "icon": "✦",
        "text": "Utilize FHSA contributions to optimize tax-free growth for the home purchase"
      }
    ],
    "rrsp": [
      {
        "icon": "⚡",
        "text": "Contribute to RRSP to reduce taxable income and optimize deferred growth"
      }
    ],
    "investment": [
      {
        "icon": "⚠",
        "text": "Monitor and adjust the portfolio's tax efficiency to minimize tax liability"
      }
    ]
  },
  "daily_outlook": "The portfolio's outlook is cautiously optimistic, with a focus on monitoring and adjusting leverage exposure and sector allocation to manage risk. The potential for growth in the tech and AI sectors, driven by adoption and innovation, is a key driver of the portfolio's performance.",
  "market_mood": "risk-on",
  "generated_at": "2026-06-02T15:20:23.176633+00:00",
  "generated_date": "June 02, 2026",
  "next_update": "6:00 AM EST next trading day"
}